discordus/__init__.py
discordus/main.py
discordus-0.3.dist-info/METADATA
discordus-0.3.dist-info/WHEEL
discordus-0.3.dist-info/entry_points.txt
discordus-0.3.dist-info/top_level.txt
discordus-0.3.dist-info/RECORD
